encodeci/__init__.py
encodeci/main.py
encodeci-0.0.1.dist-info/LICENSE
encodeci-0.0.1.dist-info/METADATA
encodeci-0.0.1.dist-info/WHEEL
encodeci-0.0.1.dist-info/top_level.txt
encodeci-0.0.1.dist-info/RECORD
