Metadata-Version: 2.1
Name: encodeci
Version: 0.0.1
Summary: A Python (cipher) encoder and decoder module
Home-page: https://github.com/kokonut27/encodeci
Author: kokonut27
Author-email: beol0127@gmail.com
License: MIT License
Platform: UNKNOWN
Classifier: Programming Language :: Python :: 3.6
Classifier: License :: OSI Approved :: MIT License
Classifier: Operating System :: OS Independent
Requires-Python: >=3.6
License-File: LICENSE
